{
  "BorderRadius": {
    "value": "2",
    "type": "other"
  },
  "FontScale": {
    "value": "1.33",
    "type": "other"
  },
  "HeightScale": {
    "value": "1.3",
    "type": "other"
  },
  "HardGrid": {
    "value": "8",
    "type": "other"
  },
  "ColorHue": {
    "value": "257",
    "type": "other"
  },
  "SurfaceHue": {
    "value": "227",
    "type": "other"
  },
  "AccentLightness": {
    "value": "65%",
    "type": "other"
  },
  "FontFamily": {
    "value": "Inter",
    "type": "fontFamilies"
  }
}